{
    "version": "2.31.0",
    "architecture": {
        "64bit": {
            "url": "https://github.com/aquaproj/aqua/releases/download/v2.31.0/aqua_windows_amd64.zip",
            "bin": [
                "aqua.exe"
            ],
            "hash": "2dd735126c139a6439767ef5cb41885a47fa0f1f04426b4a2bce4f1cb9bdd405"
        },
        "arm64": {
            "url": "https://github.com/aquaproj/aqua/releases/download/v2.31.0/aqua_windows_arm64.zip",
            "bin": [
                "aqua.exe"
            ],
            "hash": "0b9cbe177e92955135ee40cf4311240cbbbe2030eaf5c3be967bf69823a77591"
        }
    },
    "license": "MIT",
    "description": "Declarative CLI Version manager written in Go.\nSupport Lazy Install, Registry, and continuous update by Renovate.\nCLI version is switched seamlessly\n"
}