{
    "version": "2.27.1",
    "architecture": {
        "64bit": {
            "url": "https://github.com/aquaproj/aqua/releases/download/v2.27.1/aqua_windows_amd64.zip",
            "bin": [
                "aqua.exe"
            ],
            "hash": "38685829cc7ffe1b3161f1673e5c7cc3684042b4037f072dc0602cdc23c94512"
        },
        "arm64": {
            "url": "https://github.com/aquaproj/aqua/releases/download/v2.27.1/aqua_windows_arm64.zip",
            "bin": [
                "aqua.exe"
            ],
            "hash": "9060e121cb73c1411a137deac810726d36edfc8055209daa2b469df2a1befeda"
        }
    },
    "license": "MIT",
    "description": "Declarative CLI Version manager written in Go.\nSupport Lazy Install, Registry, and continuous update by Renovate.\nCLI version is switched seamlessly\n"
}